zelenium/__init__.py
zelenium/expected_conditions.py
zelenium/base/__init__.py
zelenium/base/config.py
zelenium/base/page.py
zelenium/utils/__init__.py
zelenium/utils/singleton.py
zelenium-1.0.3.dist-info/LICENSE
zelenium-1.0.3.dist-info/METADATA
zelenium-1.0.3.dist-info/WHEEL
zelenium-1.0.3.dist-info/top_level.txt
zelenium-1.0.3.dist-info/RECORD
